{
  "Coldness_SamiRouge": {
    "NAME": "냉기",
    "DESCRIPTION": "소멸. NL 손에 있는 동안 스킬 카드를 사용할 수 없습니다.",
    "UPGRADE_DESCRIPTION": "소멸 시 손으로 되돌아옵니다. NL 손에 있는 동안 스킬 카드를 사용할 수 없습니다.",
    "EXTENDED_DESCRIPTION": [
      "너무 추워……"
    ]
  },
  "Hypothermia_SamiRouge": {
    "NAME": "저체온증",
    "DESCRIPTION": "소멸. NL 손에 있는 동안 공격 카드를 사용할 수 없습니다.",
    "UPGRADE_DESCRIPTION": "소멸 시 손으로 되돌아옵니다. NL 손에 있는 동안 공격 카드를 사용할 수 없습니다.",
    "EXTENDED_DESCRIPTION": [
      "몸의 감각이 느껴지지 않아……"
    ]
  },
  "Freeze_SamiRouge": {
    "NAME": "빙결",
    "DESCRIPTION": "소멸. NL 손에 있는 동안, 다른 이름의 카드를 사용할 수 없습니다.",
    "UPGRADE_DESCRIPTION": "소멸 시 손으로 되돌아옵니다. NL 손에 있는 동안, 다른 이름의 카드를 사용할 수 없습니다.",
    "EXTENDED_DESCRIPTION": [
      "몸이…… 움직이지 않아……"
    ]
  },
  "ActivateMatrix_SamiRouge": {
    "NAME": "매트릭스 활성화",
    "DESCRIPTION": "소멸. NL 모든 적의 현실-가상 매핑 효과를 무효화합니다. 이 효과는 이 카드 외에 !M! 장의 카드를 사용할 때까지 유지됩니다."
  },

  "TeamForeverHunt_SamiRouge": {
    "NAME": "영원 사냥 Team",
    "DESCRIPTION": ""
  },

  "RelicPreviewCard_SamiRouge": {
    "NAME": "Relic Name",
    "DESCRIPTION": "Relic description",
    "EXTENDED_DESCRIPTION":[
      "The effect of this relic",
      "The Flavor of this relic"
    ]
  },

  "PastWeaveFuture_SamiRouge": {
    "NAME": "과거와 미래의 종착점",
    "DESCRIPTION": "소멸. NL 손에 있는 카드 1 장에 samirg:영원을 부여합니다.",
    "UPGRADE_DESCRIPTION": "보존. 소멸. NL 손에 있는 카드 1 장에 samirg:영원을 부여합니다."
  }
}
